{
    "profile": {
        "_id": "6960cb87631fd1743497ec8b",
        "NAAS_CD": "3CC88975",
        "AIDE_NM": "송동수, 허용",
        "BIRDY_DIV_CD": "음",
        "BIRDY_DT": "1972-12-07",
        "BLNG_CMIT_NM": "법제사법위원회, 국회운영위원회, 감사원장(김호철) 임명동의에 관한 인사청문특별위원회",
        "BRF_HST": "□ 학력\r\n- 서울대학교 법과대학 공법학과 졸업\r\n\r\n□ 주요약력\r\n- (현) 제22대 국회 부천시(을) 국회의원(법제사법위원회 위원)\r\n- (현) 민주연구원 이사\r\n- (전) 제22대 국회 국토교통위원회 위원\r\n- (전) 부천시 고문변호사\r\n- (전) 청와대 민정수석실 반부패비서관\r\n- (전) 대검찰청 검찰연구관\r\n- (전) 특수전사령부 검찰관&middot;군판사\r\n- 제30기 사법연수원 수료\r\n- 제40회 사법시험 합격",
        "CHF_SCRT_NM": "강은주, 황집필",
        "CMIT_NM": "법제사법위원회, 국회운영위원회, 감사원장(김호철) 임명동의에 관한 인사청문특별위원회",
        "CURR_ELECD_NM": "경기 부천시을",
        "CURR_PLPT_NM": "더불어민주당",
        "DTY_NM": "위원",
        "HISTORY_TIMELINE": [
            {
                "unit": 22,
                "party": "더불어민주당",
                "district": "경기 부천시을"
            }
        ],
        "NAAS_CH_NM": "金起杓",
        "NAAS_EMAIL_ADDR": "kimgipyo24@naver.com",
        "NAAS_EN_NM": "KIM GIPYO",
        "NAAS_HP_URL": "https://blog.naver.com/bucheon_lawyer",
        "NAAS_NM": "김기표",
        "NAAS_PIC": "https://www.assembly.go.kr/static/portal/img/openassm/new/f7a2f2d87cc04bd4a7e7715119a9dc6e.png",
        "NAAS_TEL_NO": "02-784-4840",
        "NTR_DIV": "남",
        "OFFM_RNUM_NO": "의원회관 324호",
        "RLCT_COUNT": 1,
        "RLCT_DIV_NM": "초선",
        "SCRT_NM": "신선미, 조민지, 김민성, 이지원, 안혜진",
        "PHOTO_PATH": "member_thumbs_300/김기표_3CC88975_300.jpg",
        "SNS_INFO": {
            "facebook": "https://web.facebook.com/gipyo.kim.12",
            "youtube": "https://www.youtube.com/@bucheon_wind24",
            "twitter": null,
            "blog": "https://blog.naver.com/bucheon_lawyer"
        },
        "is_22nd": true
    },
    "analysis": {
        "keywords": [
            "특검",
            "부천",
            "출신",
            "이날",
            "민주당",
            "시민",
            "민주",
            "시장",
            "혁신",
            "정부",
            "나경원",
            "법사위",
            "통일교",
            "종합",
            "국민"
        ],
        "keyword_frequency": [
            {
                "text": "특검",
                "value": 30
            },
            {
                "text": "부천",
                "value": 17
            },
            {
                "text": "출신",
                "value": 15
            },
            {
                "text": "이날",
                "value": 14
            },
            {
                "text": "민주당",
                "value": 13
            },
            {
                "text": "시민",
                "value": 12
            },
            {
                "text": "민주",
                "value": 12
            },
            {
                "text": "시장",
                "value": 11
            },
            {
                "text": "혁신",
                "value": 11
            },
            {
                "text": "정부",
                "value": 11
            },
            {
                "text": "나경원",
                "value": 11
            },
            {
                "text": "법사위",
                "value": 10
            },
            {
                "text": "통일교",
                "value": 10
            },
            {
                "text": "종합",
                "value": 10
            },
            {
                "text": "국민",
                "value": 10
            }
        ],
        "last_analyzed_at": "2026-02-02T09:56:59.758728",
        "trend_news": {
            "labels": [
                "01-27",
                "01-28",
                "01-29",
                "01-30",
                "01-31",
                "02-01",
                "02-02"
            ],
            "data": [
                0,
                0,
                2,
                1,
                0,
                1,
                0
            ]
        }
    },
    "recent_news": [
        {
            "_id": "697ff10038b0cf409697731b",
            "link": "https://n.news.naver.com/mnews/article/382/0001252168?sid=102",
            "created_at": "2026-02-02T09:34:08.605000",
            "description": "서명부 전달은 부천 지역 국회의원들이 발의한 막장 유튜버 제재 관련 형법 개정안의 조속한 상정과 심의를... 이건태 의원(부천시 병)도 공동 발의자로 참여했다. 앞서 시민대책위원회는 지난해 10월부터 약 3개월간... ",
            "originallink": "https://sports.donga.com/region/article/all/20260201/133270536/1",
            "press": "동아일보",
            "pubDate": "2026-02-01T02:36:00",
            "related_members": [
                "3CC88975",
                "XR24352K",
                "7YC6702R"
            ],
            "title": "조용익 부천시장 “시민과 함께 미디어 안전 도시 만들겠다”"
        },
        {
            "_id": "697cbd1e38b0cf4096976aab",
            "link": "https://n.news.naver.com/mnews/article/003/0013740658?sid=102",
            "created_at": "2026-01-30T23:15:58.728000",
            "description": "이는 부천 지역 국회의원들이 발의한 '막장 유튜버 제재 관련 형법 개정안'의 조속한 상정과 심의를 요청하기 위한 것이다. 서명에는 입법 필요성에 공감한 시민 2만여명이 참여했다. 더불어민주당 서영석(경기부천갑) 의원... ",
            "originallink": "https://www.newsis.com/view/NISX20260130_0003497268",
            "press": "뉴시스",
            "pubDate": "2026-01-30T17:30:00",
            "related_members": [
                "3CC88975",
                "XR24352K"
            ],
            "title": "부천시민사회, 국회 찾아 '막장 유튜버' 제재 입법 촉구"
        },
        {
            "_id": "697cbd1e38b0cf4096976aac",
            "link": "https://n.news.naver.com/mnews/article/052/0002307701?sid=100",
            "created_at": "2026-01-30T23:15:58.728000",
            "description": "법사위 여당 간사인 김용민 의원 등은 오늘(29일) 국회 기자회견에서, 대한민국 사법 정의는 어제 죽었다고 말했습니다. 이어 재판부가 도이치모터스 주가 조작 혐의와 관련해, 시세 조종 동원 가능성을 인식했을 여지가... ",
            "originallink": "https://www.ytn.co.kr/_ln/0101_202601291727467481",
            "press": "YTN",
            "pubDate": "2026-01-29T17:27:00",
            "related_members": [
                "TQP7167T",
                "3CC88975",
                "OFE45081"
            ],
            "title": "범여권 법사위원 \"김건희 1심, 샤넬백으로 주가조작 덮어\""
        },
        {
            "_id": "697cbd1e38b0cf4096976aad",
            "link": "https://n.news.naver.com/mnews/article/003/0013738442?sid=100",
            "created_at": "2026-01-30T23:15:58.728000",
            "description": "국회 법제사법위원 소속인 김용민·서영교·박지원·박균택·김기표·전현희 민주당 의원과 박은정 조국혁신당 의원, 최혁진 무소속 의원은 이날 국회 본회의장 앞에서 기자회견을 열고 \"권력의 핵심은 보호하고 지엽적인... ",
            "originallink": "https://www.newsis.com/view/NISX20260129_0003495490",
            "press": "뉴시스",
            "pubDate": "2026-01-29T16:20:00",
            "related_members": [
                "3CC88975",
                "8BF5855P",
                "25G2571T",
                "CC78321E",
                "1A82234K",
                "OFE45081",
                "TQP7167T",
                "TKJ4800F",
                "IWR8966I"
            ],
            "title": "與 \"법원, 김건희 봐주기 판결…입법권으로 싸울 것\""
        },
        {
            "_id": "6976fceb8459600028997f3e",
            "link": "https://n.news.naver.com/mnews/article/421/0008732861?sid=102",
            "created_at": "2026-01-26T14:34:32.940000",
            "description": "이날 출판기념회에는 김승원(민주당 경기도당위원장), 김영진, 박성준, 전용기, 김기표, 김동아, 염태영, 이건태, 이상식 국회의원, 이재준 수원특례시장, 백군기 전 용인특례시장, 이종걸, 김병욱, 양정숙, 양이원영 전... ",
            "originallink": "https://www.news1.kr/local/gyeonggi/6050012",
            "press": "뉴스1",
            "pubDate": "2026-01-25T13:11:00",
            "related_members": [
                "ATB59635",
                "URX8075K",
                "5765663F",
                "7YC6702R",
                "W8W95421",
                "IL74008M",
                "MIS62075",
                "3CC88975",
                "TJW93720",
                "3OQ8273H",
                "YM42715P",
                "6I88973D",
                "URV1689Q"
            ],
            "title": "현근택 출판기념회에 1천여명 몰려…“용인시장 선거 기대 반영”"
        },
        {
            "_id": "69701230297082fcc2b34c2c",
            "link": "https://radio.ytn.co.kr/program/?f=2&id=106945&s_mcd=0214&s_hcd=01",
            "created_at": "2026-01-21T08:39:27.077000",
            "description": "그렇다면 그 뜻을 받아 하는 국회의원이나 정부 관료들은 그 뜻에 맞게 보완수사권을 폐지하고 여러 가지 보완 장치를 다른 방면으로 고민하는 것이 옳다 생각하고 있습니다. ◇ 김기표 : 전면 재수정될지 어느 정도가... ",
            "originallink": "https://radio.ytn.co.kr/program/?f=2&id=106945&s_mcd=0214&s_hcd=01",
            "press": "YTN",
            "pubDate": "2026-01-19T09:30:00",
            "related_members": [
                "3CC88975"
            ],
            "title": "檢출신 민주 김기표 \"정경심 4년인데 尹 5년? .. 한덕수도 엄벌해야\""
        },
        {
            "_id": "69701230297082fcc2b34c2d",
            "link": "https://n.news.naver.com/mnews/article/052/0002302531?sid=100",
            "created_at": "2026-01-21T08:39:27.077000",
            "description": "□ 방송 : FM 94.5 (07:15~09:00) □ 방송일시 : 2026년 1월 19일 (월) □ 진행 : 김영수 앵커 □ 출연자 : 김기표... 일꾼들, 국회의원들이나 다른 기타 정부 관료들이 해야 될 일이라고 생각합니다. 더 이상 그런 논쟁은 무의미하다... ",
            "originallink": "https://www.ytn.co.kr/_ln/0101_202601190805502033",
            "press": "YTN",
            "pubDate": "2026-01-19T08:05:00",
            "related_members": [
                "3CC88975"
            ],
            "title": "檢출신 민주 김기표 \"정경심 4년인데 尹 5년? .. 한덕수도 엄벌해야\""
        },
        {
            "_id": "69701230297082fcc2b34c2e",
            "link": "https://radio.ytn.co.kr/program/?f=2&id=106939&s_mcd=0214&s_hcd=01",
            "created_at": "2026-01-21T08:39:27.077000",
            "description": "그렇다면 그 뜻을 받아 하는 국회의원이나 정부 관료들은 그 뜻에 맞게 보완수사권을 폐지하고 여러 가지 보완 장치를 다른 방면으로 고민하는 것이 옳다 생각하고 있습니다. ◇ 김기표 : 전면 재수정될지 어느 정도가... ",
            "originallink": "https://radio.ytn.co.kr/program/?f=2&id=106939&s_mcd=0214&s_hcd=01",
            "press": "YTN",
            "pubDate": "2026-01-19T08:00:00",
            "related_members": [
                "3CC88975"
            ],
            "title": "檢출신 민주 김기표 \"정부 검찰개혁안, 공청회서 수정 불가피... 보완수..."
        },
        {
            "_id": "69701230297082fcc2b34c2f",
            "link": "https://n.news.naver.com/mnews/article/052/0002302529?sid=100",
            "created_at": "2026-01-21T08:39:27.077000",
            "description": "□ 방송 : FM 94.5 (07:15~09:00) □ 방송일시 : 2026년 1월 19일 (월) □ 진행 : 김영수 앵커 □ 출연자 : 김기표... 일꾼들, 국회의원들이나 다른 기타 정부 관료들이 해야 될 일이라고 생각합니다. 더 이상 그런 논쟁은 무의미하다... ",
            "originallink": "https://www.ytn.co.kr/_ln/0101_202601190747113421",
            "press": "YTN",
            "pubDate": "2026-01-19T07:47:00",
            "related_members": [
                "3CC88975"
            ],
            "title": "檢출신 민주 김기표 \"정부 검찰개혁안, 공청회서 수정 불가피..보완수사..."
        },
        {
            "_id": "696c5be9297082fcc2b19b76",
            "link": "https://n.news.naver.com/mnews/article/382/0001248636?sid=102",
            "created_at": "2026-01-18T13:04:57.260000",
            "description": "이날 전달식에는 조용익 부천시장을 비롯해 서영석·이건태·김기표 국회의원이 참석했다. 총 125,842명의 시민 서명이 담긴 서명부가 국토교통부에 공식 전달됐다. 참석자들은 전달식에서 서명부에 담긴 시민들의 뜻이... ",
            "originallink": "https://sports.donga.com/region/article/all/20260116/133173693/1",
            "press": "동아일보",
            "pubDate": "2026-01-16T18:35:00",
            "related_members": [
                "XR24352K",
                "7YC6702R",
                "3CC88975"
            ],
            "title": "조용익 부천시장 “12만 시민의 절실한 목소리, 소사역 정차 필요”"
        },
        {
            "_id": "696c5be9297082fcc2b19b77",
            "link": "https://n.news.naver.com/mnews/article/016/0002587040?sid=102",
            "created_at": "2026-01-18T13:04:57.261000",
            "description": "부천시는 16일 국회의원회관 제6간담회실에서 조용익 부천시장과 서영석·이건태·김기표 국회의원 등이 참석한 가운데 12만5842명의 서명이 담긴 서명부를 국토교통부에 전달했다. 시는 그동안 서해선 KTX-이음열차의... ",
            "originallink": "https://biz.heraldcorp.com/article/10657323?ref=naver",
            "press": "헤럴드경제",
            "pubDate": "2026-01-16T18:20:00",
            "related_members": [
                "XR24352K",
                "7YC6702R",
                "3CC88975"
            ],
            "title": "부천시, 12만5천여 명 서명부 국토부 전달… 서해선 KTX-이음열차의 소..."
        },
        {
            "_id": "696c5be9297082fcc2b19b78",
            "link": "https://n.news.naver.com/mnews/article/011/0004579612?sid=102",
            "created_at": "2026-01-18T13:04:57.261000",
            "description": "조용익 부천시장은 이날 전달식에 서영석, 이건태, 김기표 국회의원과 참석해 서명이 담긴 서명부를 국토교통부 측에 전달했다. 부천시는 그동안 서해선 KTX-이음열차의 소사역 정차가 실현될 경우, 부천·인천 등 수도권... ",
            "originallink": "https://www.sedaily.com/NewsView/2K7BQIMDNY",
            "press": "서울경제",
            "pubDate": "2026-01-16T14:50:00",
            "related_members": [
                "XR24352K",
                "7YC6702R",
                "3CC88975"
            ],
            "title": "'KTX-이음열차 소사역 정차 염원' 부천시민 열망 10만 넘겼다"
        },
        {
            "_id": "6968ad89297082fcc2b18cea",
            "link": "https://n.news.naver.com/mnews/article/032/0003421820?sid=100",
            "created_at": "2026-01-15T18:04:06.224000",
            "description": "김현정 원내대변인은 이날 국회에서 열린 의원총회 뒤 기자들과 만나 “수사사법관과 전문수사관을... 변호사 출신의 김남희 의원은 이날 페이스북에 “검찰개혁만 바라보다 경찰 또는 다른 기관이 새로운 권력으로... ",
            "originallink": "https://www.khan.co.kr/article/202601151708001",
            "press": "경향신문",
            "pubDate": "2026-01-15T17:08:00",
            "related_members": [
                "7YL9580G",
                "3CC88975",
                "6VC83722",
                "NXB3178C",
                "VRY5522V",
                "I7R13867"
            ],
            "title": "민주당 의총서 중수청 이원화 비판 이어져…20일 공청회 후 당 수정안 제..."
        },
        {
            "_id": "6964b543631fd17434996026",
            "link": "https://n.news.naver.com/mnews/article/421/0008708608?sid=100",
            "created_at": "2026-01-12T17:48:00.871000",
            "description": "안건조정위에 속한 박지원 민주당 의원은 이날 국회에서 기자들과 만나 \"통일교 신천지 특검은 오늘... 현재 안건조정위는 민주당 3명(박지원 김용민 김기표), 국민의힘 2명(곽규택 주진우), 조국혁신당 1명(박은정)으로... ",
            "originallink": "https://www.news1.kr/politics/assembly/6035890",
            "press": "뉴스1",
            "pubDate": "2026-01-12T12:27:00",
            "related_members": [
                "8BF5855P",
                "OFE45081",
                "GJK57930",
                "3CC88975",
                "1A82234K",
                "REG96285"
            ],
            "title": "野 반발 속 2차특검법 법사위 안조위 통과…통일교 특검 보류(종합)"
        },
        {
            "_id": "6964b543631fd17434996027",
            "link": "https://n.news.naver.com/mnews/article/421/0008707640?sid=100",
            "created_at": "2026-01-12T17:48:00.871000",
            "description": "현재 안건조정위에는 더불어민주당 박지원·김용민·김기표 의원, 국민의힘 곽규택·주진우 의원, 조국혁신당... 이 후보자는 국회의원 재직 당시 인턴 직원에게 폭언을 했다는 주장과 보좌진에게 사적 심부름을 시키고... ",
            "originallink": "https://www.news1.kr/politics/assembly/6035120",
            "press": "뉴스1",
            "pubDate": "2026-01-12T06:00:00",
            "related_members": [
                "8BF5855P",
                "GJK57930",
                "OFE45081",
                "3CC88975",
                "REG96285",
                "1A82234K",
                "KFM1081G",
                "QWL7778X",
                "8Q88373R",
                "9YO73104",
                "MNZ4401T"
            ],
            "title": "여야 '통일교·2차 종합 특검' 충돌 전망…재경위 '이혜훈' 두고 전운"
        },
        {
            "_id": "6964b543631fd1743499602e",
            "link": "https://n.news.naver.com/mnews/article/009/0005618074?sid=100",
            "created_at": "2026-01-12T17:48:00.871000",
            "description": "이날 안건조정위는 민주당 박지원·김용민·김기표 의원, 국민의힘 곽규택·주진우 의원, 조국혁신당 박은정... 한편 국민의힘은 이날 2022년 지방선거 공천을 둘러싼 '김병기·강선우 국회의원의 공천 뇌물 수수 의혹 사건... ",
            "originallink": "https://www.mk.co.kr/article/11925991",
            "press": "매일경제",
            "pubDate": "2026-01-07T17:51:00",
            "related_members": [
                "MNZ4401T",
                "8Q88373R",
                "REG96285",
                "8BF5855P",
                "OFE45081",
                "GJK57930",
                "3CC88975",
                "1A82234K"
            ],
            "title": "與 법사위서 '쌍특검법' 강행 … 野, 공천뇌물특검 발의 맞불"
        },
        {
            "_id": "6964b546631fd1743499606f",
            "link": "https://n.news.naver.com/mnews/article/448/0000582072?sid=100",
            "created_at": "2026-01-12T17:48:04.045000",
            "description": "더민주전국혁신회의(상임대표 김기표·김문수·유동철·이광희·허태정, 이하 혁신회의)는 이날 국회 의원회관... 이날 행사장에는 김문수, 유동철, 이광희 공동상임대표를 비롯해 김우영, 박주민, 윤종군, 이재강, 조계원... ",
            "originallink": "https://news.tvchosun.com/site/data/html_dir/2026/01/07/2026010790244.html",
            "press": "조선일보",
            "pubDate": "2026-01-07T17:44:00",
            "related_members": [
                "3CC88975",
                "86R9476S",
                "95J3282H",
                "3UI95829",
                "6AU2417B",
                "3LP22204",
                "8TU8443O",
                "MQK9493H"
            ],
            "title": "與 혁신회의 \"이재명처럼 상상하고 혁신해 지방선거 승리해야\""
        },
        {
            "_id": "6964b546631fd17434996070",
            "link": "https://n.news.naver.com/mnews/article/009/0005617949?sid=100",
            "created_at": "2026-01-12T17:48:04.045000",
            "description": "이날 안건조정위는 민주당 박지원·김용민·김기표 의원, 국민의힘 곽규택·주진우 의원, 조국혁신당 박은정... ‘김병기·강선우 국회의원의 공천 뇌물 수수 의혹 사건 진상규명을 위한 특검법’을 국회 의안과에... ",
            "originallink": "https://www.mk.co.kr/article/11925830",
            "press": "매일경제",
            "pubDate": "2026-01-07T16:48:00",
            "related_members": [
                "8BF5855P",
                "8Q88373R",
                "OFE45081",
                "MNZ4401T",
                "GJK57930",
                "3CC88975",
                "1A82234K",
                "REG96285"
            ],
            "title": "민주, 종합특검·통일교특검 법사위 처리 시동…국힘, 공천뇌물 특검법..."
        },
        {
            "_id": "6964b542631fd17434996011",
            "link": "https://n.news.naver.com/mnews/article/015/0005233354?sid=100",
            "created_at": "2026-01-12T17:48:00.015000",
            "description": "2026년 1월 6일 더불어민주당 국회의원 68명 강준현·고민정·곽상언·권칠승·권향엽·김기표·김남근·김남희·김문수·김승원·김용만·김용민·김윤·김원이·김준혁·김태년·김태선·김현정·남인순·문금주·문정복·민병덕... ",
            "originallink": "https://www.hankyung.com/article/2026010644427",
            "press": "한국경제",
            "pubDate": "2026-01-06T14:33:00",
            "related_members": [
                "NB64509Z",
                "4L695580",
                "C7E79345",
                "OFE45081",
                "YM42715P",
                "GOC54665",
                "04T3751T",
                "EFU76868",
                "ATB59635",
                "TZ228122",
                "NXB3178C",
                "6VC83722",
                "FIE6569O",
                "86R9476S",
                "WCD5518S",
                "5KV96424",
                "5N65159P",
                "IUX1829H",
                "6WK3815W",
                "7YL9580G",
                "3CC88975",
                "GRP3908I",
                "1WE5693J",
                "VRY5522V",
                "BT62420K",
                "E2B3753X",
                "ZDR63255",
                "HSS7466Y",
                "XR24352K",
                "RG972910",
                "6I88973D",
                "51A45980",
                "MDC3257K",
                "GJ56729D",
                "ZW43496R",
                "CK143054",
                "JSA8739I",
                "URX8075K",
                "OIA3741M",
                "BRU2690F",
                "GP07421U",
                "JC14718Q",
                "MQK9493H",
                "7YC6702R",
                "W3U3344O",
                "95J3282H",
                "0R68099X",
                "EBH1101V",
                "9JF4562W",
                "6K79158C",
                "3ZR4438W",
                "RKS3658I",
                "3LP22204",
                "RBM5454A",
                "UQ282145",
                "2S73768V",
                "4T026790",
                "X639721U",
                "CCU1009B",
                "FH777496",
                "RPN2293B",
                "QUR40502",
                "UHB5553T",
                "3C23171A",
                "8TU8443O",
                "YS38221N",
                "BCQ55105",
                "T6A6557F"
            ],
            "title": "與 의원 68명 \"미국의 베네수엘라 군사작전, 국제평화 위협\" [전문]"
        },
        {
            "_id": "6964b542631fd17434996012",
            "link": "https://n.news.naver.com/mnews/article/028/0002784988?sid=100",
            "created_at": "2026-01-12T17:48:00.015000",
            "description": "2026년 1월 6일 더불어민주당 국회의원 68명 강준현, 고민정, 곽상언, 권칠승, 권향엽, 김기표, 김남근, 김남희, 김문수, 김승원, 김용만, 김용민, 김 윤, 김원이, 김준혁, 김태년, 김태선, 김현정, 남인순, 문금주, 문정복, 민병덕... ",
            "originallink": "https://www.hani.co.kr/arti/politics/politics_general/1238251.html",
            "press": "한겨레",
            "pubDate": "2026-01-06T11:58:00",
            "related_members": [
                "NB64509Z",
                "4L695580",
                "C7E79345",
                "OFE45081",
                "YM42715P",
                "GOC54665",
                "04T3751T",
                "EFU76868",
                "ATB59635",
                "TZ228122",
                "NXB3178C",
                "6VC83722",
                "FIE6569O",
                "86R9476S",
                "WCD5518S",
                "5KV96424",
                "IUX1829H",
                "6WK3815W",
                "7YL9580G",
                "3CC88975",
                "GRP3908I",
                "1WE5693J",
                "BT62420K",
                "VRY5522V",
                "E2B3753X",
                "ZDR63255",
                "HSS7466Y",
                "XR24352K",
                "RG972910",
                "6I88973D",
                "51A45980",
                "MDC3257K",
                "GJ56729D",
                "ZW43496R",
                "OIA3741M",
                "CK143054",
                "JSA8739I",
                "URX8075K",
                "BRU2690F",
                "MQK9493H",
                "GP07421U",
                "7YC6702R",
                "JC14718Q",
                "95J3282H",
                "0R68099X",
                "W3U3344O",
                "EBH1101V",
                "9JF4562W",
                "6K79158C",
                "3ZR4438W",
                "RKS3658I",
                "3LP22204",
                "RBM5454A",
                "UQ282145",
                "CCU1009B",
                "FH777496",
                "2S73768V",
                "4T026790",
                "X639721U",
                "RPN2293B",
                "QUR40502",
                "UHB5553T",
                "8TU8443O",
                "3C23171A",
                "YS38221N",
                "BCQ55105",
                "T6A6557F"
            ],
            "title": "민주 의원 68명 “미, 베네수엘라 군사작전은 국제평화에 심각한 위협”"
        },
        {
            "_id": "6964b546631fd17434996071",
            "link": "https://n.news.naver.com/mnews/article/421/0008685409?sid=100",
            "created_at": "2026-01-12T17:48:04.045000",
            "description": "곽 의원은 \"독자적인 교섭단체를 구성할 수 있을 정도로 민변 출신 국회의원들이 많다\"며 \"행정, 국회, 심지어... 김기표 민주당 의원은 \"정치적인 감사, 국가보다는 권력에 부역했던 사람들이 승진이나 요직에 등용되거나... ",
            "originallink": "https://www.news1.kr/politics/assembly/6023094",
            "press": "뉴스1",
            "pubDate": "2025-12-29T23:24:00",
            "related_members": [
                "3CC88975"
            ],
            "title": "김호철 청문회, 민변출신·정치편향 '쟁점'…30일 보고서 채택 논의(종합..."
        },
        {
            "_id": "6964b546631fd17434996072",
            "link": "https://n.news.naver.com/mnews/article/003/0013682135?sid=100",
            "created_at": "2026-01-12T17:48:04.045000",
            "description": "이승재 정금민 기자 = 여야는 29일 열린 김호철 감사원장 후보자에 대한 국회 인사청문회에서 자료 제출... 김기표 민주당 의원은 \"지난 윤석열 정부 시기 감사원의 정치적 중립성이 훼손됐다\"며 \"감사원 내 운영 쇄신... ",
            "originallink": "https://www.newsis.com/view/NISX20251229_0003458424",
            "press": "뉴시스",
            "pubDate": "2025-12-29T17:32:00",
            "related_members": [
                "3CC88975"
            ],
            "title": "감사원장 청문회, 野 \"민변 파벌 위험\" vs 與 \"오세훈도 민변\"…주식 보..."
        },
        {
            "_id": "6964b546631fd17434996073",
            "link": "https://n.news.naver.com/mnews/article/421/0008684241?sid=100",
            "created_at": "2026-01-12T17:48:04.045000",
            "description": "곽 의원은 \"독자적인 교섭단체를 구성할 수 있을 정도로 민변 출신 국회의원들이 많다\"며 \"행정, 국회... 김기표 민주당 의원은 \"정치적인 감사, 국가보다는 권력에 부역했던 사람들이 승진이나 요직에 등용되거나 해외... ",
            "originallink": "https://www.news1.kr/politics/assembly/6022385",
            "press": "뉴스1",
            "pubDate": "2025-12-29T12:05:00",
            "related_members": [
                "3CC88975"
            ],
            "title": "野 \"국가기관에 민변 파벌\"…與 \"감사원 유병호 타이거 파벌\"(종합)"
        },
        {
            "_id": "6964b546631fd17434996074",
            "link": "https://n.news.naver.com/mnews/article/421/0008662521?sid=100",
            "created_at": "2026-01-12T17:48:04.045000",
            "description": "이날 오전 국회 의원회관에서 열린 비공개회의엔 정청래 대표와 김병기 원내대표, 문진석 원내수석부대표... 법사위에선 추미애 위원장과 박지원 서영교 장경태 김기표 박균택 의원이 자리했다. 문 원내수석은 회동 뒤... ",
            "originallink": "https://www.news1.kr/politics/assembly/6009668",
            "press": "뉴스1",
            "pubDate": "2025-12-16T09:24:00",
            "related_members": [
                "4U29186R",
                "URV1689Q",
                "8BF5855P",
                "RPN2293B",
                "2385336L",
                "8Q88373R",
                "IWR8966I",
                "3CC88975",
                "TKJ4800F"
            ],
            "title": "與지도부-법사위, 내란전담재판부 입장 공유…의총서 최종 결정"
        },
        {
            "_id": "6964b546631fd17434996075",
            "link": "https://n.news.naver.com/mnews/article/023/0003947153?sid=100",
            "created_at": "2026-01-12T17:48:04.045000",
            "description": "경찰이 이날 통일교 측으로부터 수천만원대 돈과 시계를 받은 의혹이 있는 전재수 민주당 의원의 국회의원 사무실을 압수수색했지만, 국민의힘 의혹과는 차이가 있다는 것이다. 김기표 민주당 원내부대표도 이날 방송에... ",
            "originallink": "https://www.chosun.com/politics/assembly/2025/12/16/TRCRYTSYRJD25HXEMWCSVTJU34/?utm_source=naver&utm_medium=referral&utm_campaign=naver-news",
            "press": "조선일보",
            "pubDate": "2025-12-16T00:53:00",
            "related_members": [
                "9YO73104",
                "3CC88975"
            ],
            "title": "與, 통일교 특검 거부하면서 “특검이 만능이냐”"
        }
    ],
    "recent_videos": [
        {
            "_id": "69659522887d07f7ba2fabbd",
            "url": "https://www.youtube.com/watch?v=k-BPST-knLE",
            "HG_NM": "김기표",
            "MONA_CD": "3CC88975",
            "collected_at": "2026-01-30T23:18:54.165000",
            "duration": 230.0,
            "title": "\"나경원과 장경태 건이 같아요?!!!\" 검사출신 김기표의원의 팩트 폭격",
            "upload_date": null
        },
        {
            "_id": "69659522887d07f7ba2fabbb",
            "url": "https://www.youtube.com/watch?v=qTzucZJDRfM",
            "HG_NM": "김기표",
            "MONA_CD": "3CC88975",
            "collected_at": "2026-02-02T09:40:31.897000",
            "duration": 456.0,
            "title": "사법권 독립 외치는 천대엽 향한 김기표 칼날 질의",
            "upload_date": null
        },
        {
            "_id": "6960abd0631fd1743497d3e1",
            "url": "https://www.youtube.com/watch?v=OEgSuMqzzh4",
            "HG_NM": "김기표",
            "MONA_CD": "3CC88975",
            "collected_at": "2026-01-09T16:18:36.623000",
            "duration": 965.0,
            "title": "돈을 셌지만 띠지는 모른다? 경력직답게 날카롭게 파고드는 김기표",
            "upload_date": null
        },
        {
            "_id": "69659522887d07f7ba2fabbf",
            "url": "https://www.youtube.com/watch?v=N0np5Re0BGs",
            "HG_NM": "김기표",
            "MONA_CD": "3CC88975",
            "collected_at": "2026-01-14T10:15:06.753000",
            "duration": 328.0,
            "title": "[자막] 김기표 \"국민의힘, 무조건 반대하다 논리 모순… 내란 행위 동조자들 특검 반대 말고 쌍수 들고 환영하라\"",
            "upload_date": null
        },
        {
            "_id": "69659522887d07f7ba2fabc2",
            "url": "https://www.youtube.com/watch?v=G5B0Xl5eteU",
            "HG_NM": "김기표",
            "MONA_CD": "3CC88975",
            "collected_at": "2026-02-02T09:40:33.386000",
            "duration": 346.0,
            "title": "[생중계] 김기표 더불어민주당 의원 현안 관련 기자회견 (2025.11.10 오후)",
            "upload_date": null
        },
        {
            "_id": "6960abd0631fd1743497d3e5",
            "url": "https://www.youtube.com/watch?v=NNO_mjJw7Ig",
            "HG_NM": "김기표",
            "MONA_CD": "3CC88975",
            "collected_at": "2026-01-21T08:41:53.811000",
            "duration": 178.0,
            "title": "박상용 검사, 연어회 술 파티가 이래도 가짜뉴스라고? #김기표 #국회의원 #더불어민주당 #부천시을",
            "upload_date": null
        },
        {
            "_id": "6966ee1a887d07f7ba2fb37e",
            "url": "https://www.youtube.com/watch?v=k96HEbInmQs",
            "HG_NM": "김기표",
            "MONA_CD": "3CC88975",
            "collected_at": "2026-01-15T18:14:10.162000",
            "duration": 61.0,
            "title": "김기표의원 나경원의원에게 누더기 법안? 정략적 특검? #김기표 #나경원 #법사위",
            "upload_date": null
        },
        {
            "_id": "6960abd0631fd1743497d3de",
            "url": "https://www.youtube.com/watch?v=UVOiCL0oMy0",
            "HG_NM": "김기표",
            "MONA_CD": "3CC88975",
            "collected_at": "2026-01-21T08:41:52.994000",
            "duration": 125.0,
            "title": "나경원, “초선 의원은 조용히 해라. 뭘 안다고” #김기표 #국회의원 #더불어민주당 #부천시을",
            "upload_date": null
        },
        {
            "_id": "69659522887d07f7ba2fabc0",
            "url": "https://www.youtube.com/watch?v=tbg13YIs1Nw",
            "HG_NM": "김기표",
            "MONA_CD": "3CC88975",
            "collected_at": "2026-02-02T09:40:33.386000",
            "duration": 534.0,
            "title": "[모닝콜] 김기표 \"'김건희 특검' 수사 대상에 심우정 포함해야\" (2025.06.25/뉴스투데이/MBC)",
            "upload_date": null
        },
        {
            "_id": "6960abd0631fd1743497d3e2",
            "url": "https://www.youtube.com/watch?v=N2mHatt3Ego",
            "HG_NM": "김기표",
            "MONA_CD": "3CC88975",
            "collected_at": "2026-01-30T23:18:54.165000",
            "duration": 440.0,
            "title": "희대의 답변에 대한 김기표 의원의 일침!!",
            "upload_date": null
        },
        {
            "_id": "69659522887d07f7ba2fabbe",
            "url": "https://www.youtube.com/watch?v=ZM7mS2dFD6s",
            "HG_NM": "김기표",
            "MONA_CD": "3CC88975",
            "collected_at": "2026-01-13T09:43:12.944000",
            "duration": 486.0,
            "title": "\"그럼 방첩사가 수사할까요?\" 김기표 의원, 나경원 의원 논리 완전 박살, 조목 조목 반박하며 격파하는데.. 나경원 의원 표정이...",
            "upload_date": null
        },
        {
            "_id": "69659522887d07f7ba2fabba",
            "url": "https://www.youtube.com/watch?v=fOogptmAczQ",
            "HG_NM": "김기표",
            "MONA_CD": "3CC88975",
            "collected_at": "2026-02-02T09:40:31.897000",
            "duration": 741.0,
            "title": "\"윤석열 정부 때 승진했죠?\"  ... 김기표, 대검 문서감정실장에 묻자 '발끈'",
            "upload_date": null
        },
        {
            "_id": "6960abd0631fd1743497d3e4",
            "url": "https://www.youtube.com/watch?v=NDUc-iusfB8",
            "HG_NM": "김기표",
            "MONA_CD": "3CC88975",
            "collected_at": "2026-01-09T16:18:37.438000",
            "duration": 307.0,
            "title": "[자막] 특검이 돈낭비라는 국민의힘? 김기표, \"윤석열 정권 대왕고래 예산이면 특검 충분\"",
            "upload_date": null
        },
        {
            "_id": "69659522887d07f7ba2fabb9",
            "url": "https://www.youtube.com/watch?v=rOpDqpvj90k",
            "HG_NM": "김기표",
            "MONA_CD": "3CC88975",
            "collected_at": "2026-02-02T09:40:33.386000",
            "duration": 202.0,
            "title": "\"전한길, 전광훈을 임명할까요?\"... 김기표, 뼈 때리는 발언에 국힘..",
            "upload_date": null
        },
        {
            "_id": "6960abd0631fd1743497d3e0",
            "url": "https://www.youtube.com/watch?v=3GCa8LaaZks",
            "HG_NM": "김기표",
            "MONA_CD": "3CC88975",
            "collected_at": "2026-01-21T08:41:52.994000",
            "duration": 88.0,
            "title": "국회의원 김기표,특수부 검사에서 국회의원이 되기까지 #김기표 #국회의원 #더불어민주당 #법사위원",
            "upload_date": null
        },
        {
            "_id": "6960abd0631fd1743497d3e6",
            "url": "https://www.youtube.com/watch?v=7P7AxT-8IXM",
            "HG_NM": "김기표",
            "MONA_CD": "3CC88975",
            "collected_at": "2026-01-21T08:41:53.811000",
            "duration": 172.0,
            "title": "물어볼수록 드러나는 거짓말 범벅 대법원 판결문!! #국회의원 #김기표 #더불어민주당 #부천시을 #법제사법위원회 #대법원 #국정감사 #조희대 #파기환송 #이재명",
            "upload_date": null
        },
        {
            "_id": "6960abd0631fd1743497d3dd",
            "url": "https://www.youtube.com/watch?v=UCqUIRTYoiQRpaP6EifVmsIA",
            "HG_NM": "김기표",
            "MONA_CD": "3CC88975",
            "collected_at": "2026-02-02T09:40:31.897000",
            "duration": null,
            "title": "부천 김기표 TV",
            "upload_date": null
        },
        {
            "_id": "6960abd0631fd1743497d3df",
            "url": "https://www.youtube.com/watch?v=IkVmBTvcTbg",
            "HG_NM": "김기표",
            "MONA_CD": "3CC88975",
            "collected_at": "2026-01-09T16:18:36.623000",
            "duration": 464.0,
            "title": "\"그건 외부음식 아닙니까?\"...잡아떼던 박상용, 김기표 송곳 질의에 '얼음'",
            "upload_date": null
        },
        {
            "_id": "6960abd0631fd1743497d3e3",
            "url": "https://www.youtube.com/watch?v=WLZM1bBPtBk",
            "HG_NM": "김기표",
            "MONA_CD": "3CC88975",
            "collected_at": "2026-01-09T16:18:37.438000",
            "duration": 315.0,
            "title": "\"특검 언제까지 우려먹냐고?\"...김기표, 국힘 논리 '되치기'",
            "upload_date": null
        },
        {
            "_id": "69659522887d07f7ba2fabc1",
            "url": "https://www.youtube.com/watch?v=wMltA097hbk",
            "HG_NM": "김기표",
            "MONA_CD": "3CC88975",
            "collected_at": "2026-01-13T09:43:12.944000",
            "duration": 333.0,
            "title": "\"지방선거 핑계 대지 마\" 김기표, 국힘 송석준-나경원에 비판 작렬",
            "upload_date": null
        }
    ],
    "exported_at": "2026-02-02T09:56:59.758728"
}