{
    "profile": {
        "_id": "6960cb92631fd1743497f0ae",
        "NAAS_CD": "CAA7713A",
        "AIDE_NM": "김영상, 오정석",
        "BIRDY_DIV_CD": "음",
        "BIRDY_DT": "1962-12-23",
        "BLNG_CMIT_NM": "보건복지위원회",
        "BRF_HST": "[ 학   력]\r\n\r\n- 명륜초등학교 졸업\r\n- 동해중학교 졸업\r\n- 브니엘고등학교 졸업\r\n- 부산산업대 (현 경성대학교) 화학 학사\r\n- 부산대학교 환경대학원 도시계획학 석사\r\n\r\n\r\n\r\n\r\n[ 경   력 ]\r\n\r\n- 現 제21대 부산 금정구 국회의원\r\n- 現 제21대 국회 보건복지위원회 위원\r\n- 前 (주) 백산금속 대표이사\r\n- 부산광역시의회 의장 (제7대 후반기)\r\n- 前 자유한국당 부산시당 금정구 당협위원장\r\n- 제 4, 5, 6, 7대 부산광역시의회 의원\r\n- 제6대 부산광역시의회 전반기, 후반기 부의장\r\n- 제7대 부산광역시의회 전반기 새누리당 원내대표\r\n- 前 새마을문고 부산시지부부회장\r\n- 前 부산장애인총연합회 금정구지부 후원회장\r\n- 前 한국자유총연맹 금정구지부 부지부장\r\n- 前 금정소방서 의용소방대장",
        "CHF_SCRT_NM": "신상윤, 이재희",
        "CMIT_NM": "보건복지위원회",
        "CURR_ELECD_NM": "부산 금정구",
        "CURR_PLPT_NM": "국민의힘",
        "DTY_NM": "위원",
        "HISTORY_TIMELINE": [
            {
                "unit": 21,
                "party": "미래통합당",
                "district": "부산 금정구"
            },
            {
                "unit": 22,
                "party": "국민의힘",
                "district": "부산 금정구"
            }
        ],
        "NAAS_CH_NM": "白宗憲",
        "NAAS_EMAIL_ADDR": "bjh438@naver.com",
        "NAAS_EN_NM": "BAEK JONGHEAN",
        "NAAS_HP_URL": null,
        "NAAS_NM": "백종헌",
        "NAAS_PIC": "https://www.assembly.go.kr/static/portal/img/openassm/new/335e79371cec41a7991431788b9fead9.jpg",
        "NAAS_TEL_NO": "02-784-3977",
        "NTR_DIV": "남",
        "OFFM_RNUM_NO": "의원회관 438호",
        "RLCT_COUNT": 2,
        "RLCT_DIV_NM": "재선",
        "SCRT_NM": "정진수, 박수향, 허정훈, 윤나희",
        "PHOTO_PATH": "member_thumbs_300/백종헌_CAA7713A_300.jpg",
        "SNS_INFO": {
            "facebook": null,
            "youtube": null,
            "twitter": null,
            "blog": null
        },
        "is_22nd": true
    },
    "analysis": {
        "keywords": [
            "종헌",
            "부산",
            "통일교",
            "부산시",
            "국민",
            "정치권",
            "지역",
            "국립공원",
            "금정구",
            "김도읍",
            "김대식",
            "새해",
            "선거",
            "관리",
            "체계"
        ],
        "keyword_frequency": [
            {
                "text": "종헌",
                "value": 30
            },
            {
                "text": "부산",
                "value": 19
            },
            {
                "text": "통일교",
                "value": 9
            },
            {
                "text": "부산시",
                "value": 8
            },
            {
                "text": "국민",
                "value": 7
            },
            {
                "text": "정치권",
                "value": 6
            },
            {
                "text": "지역",
                "value": 5
            },
            {
                "text": "국립공원",
                "value": 5
            },
            {
                "text": "금정구",
                "value": 5
            },
            {
                "text": "김도읍",
                "value": 4
            },
            {
                "text": "김대식",
                "value": 4
            },
            {
                "text": "새해",
                "value": 4
            },
            {
                "text": "선거",
                "value": 4
            },
            {
                "text": "관리",
                "value": 4
            },
            {
                "text": "체계",
                "value": 4
            }
        ],
        "last_analyzed_at": "2026-01-15T18:29:47.848001",
        "trend_news": {
            "labels": [
                "01-09",
                "01-10",
                "01-11",
                "01-12",
                "01-13",
                "01-14",
                "01-15"
            ],
            "data": [
                0,
                0,
                0,
                0,
                0,
                0,
                0
            ]
        }
    },
    "recent_news": [
        {
            "_id": "6964b548631fd1743499608c",
            "link": "https://n.news.naver.com/mnews/article/382/0001245651?sid=102",
            "created_at": "2026-01-12T17:48:05.254000",
            "description": "또한 조경태·이헌승·김도읍·김희정·백종헌·박수영·이성권·김미애·김대식·조승환·정연욱·정성국·곽규택·서지영·주진우 의원 등 부산지역 국회의원과 기초단체장, 주요 당직자들이 대거 자리해 2026년 부산의 미래... ",
            "originallink": "https://sports.donga.com/region/article/all/20260103/133085292/1",
            "press": "동아일보",
            "pubDate": "2026-01-03T12:11:00",
            "related_members": [
                "WXJ8352N",
                "CGW7415Z",
                "P7U7800Z",
                "ME83002L",
                "FU87526G",
                "HRG9655C",
                "8XE7026P",
                "LH97552Q",
                "5KV82250",
                "EVH1507C",
                "ANS8383S",
                "GJK57930",
                "CAA7713A",
                "3BC6890E",
                "REG96285",
                "DAY6557K"
            ],
            "title": "국민의힘 부산시당 “지방선거 필승”… 병오년 신년인사회 개최"
        },
        {
            "_id": "6964b556631fd174349961b3",
            "link": "https://n.news.naver.com/mnews/article/079/0004101370?sid=102",
            "created_at": "2026-01-12T17:48:19.834000",
            "description": "정동만 시당위원장을 비롯해 김도읍, 이헌승, 김희정, 박수영, 백종헌 의원 등 부산 지역 국회의원들과 박형준 부산시장, 안성민 부산시의회 의장, 기초단체장, 광역·기초의원 등이 대거 참석해 지방선거 승리를... ",
            "originallink": "https://www.nocutnews.co.kr/news/6450943?utm_source=naver&utm_medium=article&utm_campaign=20260102050845",
            "press": "노컷뉴스",
            "pubDate": "2026-01-02T17:09:00",
            "related_members": [
                "DAY6557K",
                "FU87526G",
                "HRG9655C",
                "LH97552Q",
                "EVH1507C",
                "CAA7713A"
            ],
            "title": "부산 정치권, 새해부터 선거 시동…여야·진보정당 신년 일정 가동"
        },
        {
            "_id": "6964b564631fd174349962ab",
            "link": "https://n.news.naver.com/mnews/article/005/0001822710?sid=103",
            "created_at": "2026-01-12T17:48:33.773000",
            "description": "백종헌 주진우 국회의원 또한 부산이 하나님의 축복 아래 더욱 멋진 도시로 성장할 수 있도록 정책적 뒷받침을 아끼지 않겠다고 약속했다. 이들은 성탄의 복음이 부산 시민들의 삶 곳곳에 희망의 불씨가 되기를 기원했다.... ",
            "originallink": "https://www.kmib.co.kr/article/view.asp?arcid=0029170413&code=61221111&cp=nv",
            "press": "국민일보",
            "pubDate": "2025-12-27T15:41:00",
            "related_members": [
                "CAA7713A",
                "GJK57930",
                "8XE7026P"
            ],
            "title": "“부산이 변해야 나라가 산다”…부산 기독교계, 연합과 도약의 새해 선..."
        },
        {
            "_id": "6964b564631fd174349962ac",
            "link": "https://n.news.naver.com/mnews/article/022/0004093223?sid=102",
            "created_at": "2026-01-12T17:48:33.773000",
            "description": "국립공원공단 제공 토론회에는 주대영 국립공원공단 이사장과 손영신 부산일보 사장, 김석준 부산시교육감, 백종헌 국회의원, 범어사 정오 주지스님을 비롯한 금정산국립공원이 위치한 7개 지방자치단체 실무진 등 중앙... ",
            "originallink": "https://www.segye.com/newsView/20251226503144?OutUrl=naver",
            "press": "세계일보",
            "pubDate": "2025-12-27T06:21:00",
            "related_members": [
                "CAA7713A"
            ],
            "title": "민·관·언 협력으로 금정산국립공원 지속가능한 관리체계 구축한다"
        },
        {
            "_id": "6964b564631fd174349962ad",
            "link": "https://n.news.naver.com/mnews/article/005/0001822032?sid=101",
            "created_at": "2026-01-12T17:48:33.773000",
            "description": "개소식에는 박순호 세정그룹 회장을 비롯해 백종헌 국회의원, 윤일현 금정구청장, 이준호 부산시의원, 박해영 남광종합사회복지관 관장, 신요한 금정구지역자활센터장, 심현녀 세정나눔재단 이사 등이 참석했다. 구서... ",
            "originallink": "https://www.kmib.co.kr/article/view.asp?arcid=0029154691&code=61141111&cp=nv",
            "press": "국민일보",
            "pubDate": "2025-12-23T14:48:00",
            "related_members": [
                "CAA7713A"
            ],
            "title": "세정, 부동산 자산을 사회적 가치로… 장애인 재활센터 입점 지원"
        },
        {
            "_id": "6964b564631fd174349962ae",
            "link": "https://n.news.naver.com/mnews/article/421/0008668883?sid=102",
            "created_at": "2026-01-12T17:48:33.773000",
            "description": "통일교와의 접촉을 전면 부인했던 김대식 국회의원(국민의힘, 부산 사상구)이 지난해 통일교 계열 교회에서... 또 백종헌 의원(국민의힘, 부산 금정구)도 2022년 대선 당시 국민의힘 부산시당위원장으로서 통일교 인사와... ",
            "originallink": "https://www.news1.kr/local/busan-gyeongnam/6013390",
            "press": "뉴스1",
            "pubDate": "2025-12-18T17:11:00",
            "related_members": [
                "CAA7713A",
                "ANS8383S"
            ],
            "title": "\"나는 안 갔다\"던 김대식 의원, 통일교 교회서 차담회"
        },
        {
            "_id": "6964b564631fd174349962af",
            "link": "https://busanmbc.co.kr/01_new/new01_view.asp?idx=281178",
            "created_at": "2026-01-12T17:48:33.773000",
            "description": "[백종헌 / 국회의원]\"개인적으로 접촉한 일이 없는데요. 시당위원장으로서 오시는 여러 가지 단체들 엄청나게 많잖아요. 그분들 오시면 30분 단위로 계속 끊어서 계속 오시면 사진 찍고 가시고 가시고 계속 그런 상황 중에.... ",
            "originallink": "https://busanmbc.co.kr/01_new/new01_view.asp?idx=281178",
            "press": "MBC",
            "pubDate": "2025-12-17T21:12:00",
            "related_members": [
                "CAA7713A"
            ],
            "title": "통일교 5지구 간부, 정치권 로비 핵심 창구"
        },
        {
            "_id": "6964b564631fd174349962b0",
            "link": "https://n.news.naver.com/mnews/article/079/0004096805?sid=102",
            "created_at": "2026-01-12T17:48:33.773000",
            "description": "대응\" 백종헌 \"사진 보고 알았다…기억 안 날 만큼 스친 만남\" 서병수·오거돈 전 시장 이력도 재조명…과거... 현 국회의원도 과거 부산시 경제부시장 재직 시 시장을 대신해 각종 행사에 참석해 축사를 한 사례가 있다\"고... ",
            "originallink": "https://www.nocutnews.co.kr/news/6444260?utm_source=naver&utm_medium=article&utm_campaign=20251217101001",
            "press": "노컷뉴스",
            "pubDate": "2025-12-17T10:11:00",
            "related_members": [
                "9YO73104",
                "CAA7713A"
            ],
            "title": "\"옷깃만 스쳐도…\" 전재수 '통일교 금품 의혹' 파문, 부산 정치권 전반..."
        }
    ],
    "recent_videos": [
        {
            "_id": "6960acc5631fd1743497d7cd",
            "url": "https://www.youtube.com/watch?v=Lqr1-KyCSTw",
            "HG_NM": "백종헌",
            "MONA_CD": "CAA7713A",
            "collected_at": "2026-01-14T10:19:06.315000",
            "duration": 579.0,
            "title": "제21대 국회 \"300인의 희망인터뷰\" 백종헌 의원(국민의힘)",
            "upload_date": null
        },
        {
            "_id": "6960acc5631fd1743497d7ce",
            "url": "https://www.youtube.com/watch?v=jHlL1e2xXYE",
            "HG_NM": "백종헌",
            "MONA_CD": "CAA7713A",
            "collected_at": "2026-01-15T18:18:28.175000",
            "duration": 118.0,
            "title": "[KBS뉴스] 20.12 (백종헌의원 권덕철 장관후보자 인사청문회 질의) ‘친문의 선거중립’·‘백신’ 청문회…변창흠은 ‘불쑥 사과’ / KBS",
            "upload_date": null
        },
        {
            "_id": "6960acc5631fd1743497d7c9",
            "url": "https://www.youtube.com/watch?v=0UC2fFCy9wc",
            "HG_NM": "백종헌",
            "MONA_CD": "CAA7713A",
            "collected_at": "2026-01-15T18:18:27.480000",
            "duration": 325.0,
            "title": "[백종헌 국회의원] 제400회 국회(정기회) 제07차 본회의 5분 발언",
            "upload_date": null
        },
        {
            "_id": "6960acc5631fd1743497d7cc",
            "url": "https://www.youtube.com/watch?v=60hDudD8-3E",
            "HG_NM": "백종헌",
            "MONA_CD": "CAA7713A",
            "collected_at": "2026-01-14T10:19:06.315000",
            "duration": 2544.0,
            "title": "부산 시의장에서 국회의원으로, 애민정치를 실현하고자 국회로 왔습니다 (feat. 백종헌 의원) [오유경의 인생책방 144회]",
            "upload_date": null
        },
        {
            "_id": "6960acc5631fd1743497d7ca",
            "url": "https://www.youtube.com/watch?v=MDlEuFmHDrM",
            "HG_NM": "백종헌",
            "MONA_CD": "CAA7713A",
            "collected_at": "2026-01-15T18:18:27.480000",
            "duration": 162.0,
            "title": "[2025 국정감사 우수의원] 국회 보건복지위 백종헌 의원 #국회 #국회의원 #국정감사 #농림축산식품해양수산위원회 #보건복지위원회 #농림축산식품부 #보건복지부 #식약처 #우수상",
            "upload_date": null
        },
        {
            "_id": "6960acc5631fd1743497d7c8",
            "url": "https://www.youtube.com/watch?v=UCU8RCbMQPk9AiipVWZeWLwA",
            "HG_NM": "백종헌",
            "MONA_CD": "CAA7713A",
            "collected_at": "2026-01-15T18:18:27.480000",
            "duration": null,
            "title": "백종헌Tv",
            "upload_date": null
        },
        {
            "_id": "6960acc5631fd1743497d7c6",
            "url": "https://www.youtube.com/watch?v=LCCbEB2e5x0",
            "HG_NM": "백종헌",
            "MONA_CD": "CAA7713A",
            "collected_at": "2026-01-15T18:18:27.480000",
            "duration": 126.0,
            "title": "국회의원 백종헌 부산 금정구 지역보고서 (5.30~7.24 )",
            "upload_date": null
        },
        {
            "_id": "6960abdc631fd1743497d417",
            "url": "https://www.youtube.com/watch?v=G-kN3LeBNxA",
            "HG_NM": "백종헌",
            "MONA_CD": "CAA7713A",
            "collected_at": "2026-01-15T18:18:28.175000",
            "duration": 192.0,
            "title": "[국회의원 성적표]③ 국회 발언량…김도읍 ‘우수’·백종헌 ‘미흡’ / KBS  2023.02.06.",
            "upload_date": null
        },
        {
            "_id": "6960acc5631fd1743497d7c7",
            "url": "https://www.youtube.com/watch?v=qkDFc3-xJJ8",
            "HG_NM": "백종헌",
            "MONA_CD": "CAA7713A",
            "collected_at": "2026-01-15T18:18:27.480000",
            "duration": 427.0,
            "title": "[백종헌 국회의원] 백종헌 의원 “노인일자리 사업, 중도포기자와 대기자 늘지만 참여 이력 관리는 0건” (241021)",
            "upload_date": null
        },
        {
            "_id": "6960acc5631fd1743497d7cb",
            "url": "https://www.youtube.com/watch?v=ALUmM0ytfkM",
            "HG_NM": "백종헌",
            "MONA_CD": "CAA7713A",
            "collected_at": "2026-01-15T18:18:28.175000",
            "duration": 146.0,
            "title": "[국회는 지금] 백종헌 국회의원 \"소아 필수 의료체계 강화해야\"",
            "upload_date": null
        }
    ],
    "exported_at": "2026-01-15T18:29:47.848001"
}